<materialLib name="Simple">
    <shaders>
        <shader name="V1" vs="shaders/simple.vert" ps="shaders/simple.frag"/>
    </shaders>
    <materials>
        <material name="V1">
            <shader name="V1">
                <values>
                    <valueof uniform="m_pvm"
                             type="RENDERER"
                             context="CURRENT"
                             component="PROJECTION_VIEW_MODEL" />
                </values>
            </shader>
        </material>
    </materials>
</materialLib>